LICENSE.txt
MANIFEST.in
README.md
pyproject.toml
tox.ini
docs/api-reference.rst
docs/code-of-conduct.md
docs/conf.py
docs/contributing.md
docs/design-and-architecture.md
docs/getting-started.md
docs/index.rst
docs/requirements.txt
docs/_static/css/custom.css
src/danoan/word_guru/__init_.py
src/danoan/word_guru/cli/__init__.py
src/danoan/word_guru/cli/cli.py
src/danoan/word_guru/cli/exception.py
src/danoan/word_guru/cli/model.py
src/danoan/word_guru/cli/utils.py
src/danoan/word_guru/cli/commands/__init__.py
src/danoan/word_guru/cli/commands/copywriter.py
src/danoan/word_guru/cli/commands/dictionary.py
src/danoan/word_guru/cli/commands/setup.py
src/danoan/word_guru/cli/commands/translate.py
src/danoan/word_guru/cli/commands/copywriter_commands/__init__.py
src/danoan/word_guru/cli/commands/copywriter_commands/get_correction.py
src/danoan/word_guru/cli/commands/dictionary_commands/__init__.py
src/danoan/word_guru/cli/commands/dictionary_commands/get_definition.py
src/danoan/word_guru/cli/commands/dictionary_commands/get_pos_tag.py
src/danoan/word_guru/cli/commands/dictionary_commands/get_reverse_definition.py
src/danoan/word_guru/cli/commands/dictionary_commands/get_synonym.py
src/danoan/word_guru/cli/commands/dictionary_commands/get_usage_examples.py
src/danoan/word_guru/core/__init__.py
src/danoan/word_guru/core/api.py
src/danoan/word_guru/core/exception.py
src/danoan/word_guru/prompts/get-complete-definition.txt
src/danoan/word_guru/prompts/get-correction.txt
src/danoan/word_guru/prompts/get-pos-tag.txt
src/danoan/word_guru/prompts/get-reverse-definition.txt
src/danoan/word_guru/prompts/get-simple-definition.txt
src/danoan/word_guru/prompts/get-synonym.txt
src/danoan/word_guru/prompts/get-translation.txt
src/danoan/word_guru/prompts/get-usage-examples.txt
src/word_guru.egg-info/PKG-INFO
src/word_guru.egg-info/SOURCES.txt
src/word_guru.egg-info/dependency_links.txt
src/word_guru.egg-info/entry_points.txt
src/word_guru.egg-info/requires.txt
src/word_guru.egg-info/top_level.txt