Metadata-Version: 2.1
Name: word-guru
Version: 0.1.0
Summary: Your language expert
Author-email: Daniel Martins Antunes <danoan2008@gmail.com>
License: MIT License
Project-URL: Documentation, https://github.com/danoan/word-guru#readme
Project-URL: Issues, https://github.com/danoan/word-guru
Project-URL: Source, https://github.com/danoan/word-guru
Classifier: Development Status :: 4 - Beta
Classifier: Programming Language :: Python
Classifier: Programming Language :: Python :: 3.8
Classifier: Programming Language :: Python :: Implementation :: CPython
Classifier: Programming Language :: Python :: Implementation :: PyPy
Requires-Python: >=3.8
License-File: LICENSE.txt
Requires-Dist: openai
Requires-Dist: jinja2
Requires-Dist: pycountry
Requires-Dist: toml-dataclass
